timequota/__init__.py
timequota/timequota.py
timequota-0.0.6.dist-info/LICENSE
timequota-0.0.6.dist-info/METADATA
timequota-0.0.6.dist-info/WHEEL
timequota-0.0.6.dist-info/top_level.txt
timequota-0.0.6.dist-info/RECORD
