Metadata-Version: 2.1
Name: timequota
Version: 0.0.6
Summary: Manage the time of your script
Home-page: https://aravrs.github.io/timequota
Author: AravRS
License: MIT
Project-URL: Source, https://github.com/AravRS/timequota
Project-URL: Documentation, https://aravrs.github.io/timequota/timequota
Project-URL: Changelog, https://github.com/aravrs/timequota/blob/main/CHANGELOG.md
Platform: UNKNOWN
Classifier: Programming Language :: Python :: 3
Classifier: License :: OSI Approved :: MIT License
Classifier: Operating System :: OS Independent
License-File: LICENSE
Requires-Dist: colorama
Requires-Dist: tabulate
Requires-Dist: typeguard
